yahoo_fin_api/__init__.py
yahoo_fin_api/client.py
yahoo_fin_api/universe.py
yahoo_fin_api/utils.py
yahoo_fin_api/yahooapi.py
yahoo_fin_api/cache/__init__.py
yahoo_fin_api/cache/base_cache.py
yahoo_fin_api/cache/file_cache.py
yahoo_fin_api/models/__init__.py
yahoo_fin_api/models/balance_sheet.py
yahoo_fin_api/models/base_model.py
yahoo_fin_api/models/cashflow.py
yahoo_fin_api/models/financial_data.py
yahoo_fin_api/models/income_statement.py
yahoo_fin_api/models/key_statistics.py
yahoo_fin_api/models/quote.py
yahoo_fin_api/models/summary_detail.py
yahoo_fin_api/models/ticker.py
yahoo_fin_api-0.0.21.dist-info/METADATA
yahoo_fin_api-0.0.21.dist-info/WHEEL
yahoo_fin_api-0.0.21.dist-info/top_level.txt
yahoo_fin_api-0.0.21.dist-info/RECORD
