Metadata-Version: 2.1
Name: yahoo-fin-api
Version: 0.0.21
Summary: Pyhton Yahoo Financials SDK
Home-page: https://github.com/MihaiBlebea/yahoo-fin-api
Author: Mihai Blebea
Author-email: mihaiserban.blebea@gmail.com
License: MIT
Keywords: yahoo financials trading api
Platform: UNKNOWN
Requires-Dist: requests
